odoo/addons/sale_cart/README.rst
odoo/addons/sale_cart/__init__.py
odoo/addons/sale_cart/__manifest__.py
odoo/addons/sale_cart/hooks.py
odoo/addons/sale_cart/i18n/fr.po
odoo/addons/sale_cart/i18n/sale_cart.pot
odoo/addons/sale_cart/models/__init__.py
odoo/addons/sale_cart/models/payment_transaction.py
odoo/addons/sale_cart/models/sale_order.py
odoo/addons/sale_cart/readme/CONTRIBUTORS.rst
odoo/addons/sale_cart/readme/DESCRIPTION.rst
odoo/addons/sale_cart/static/description/index.html
odoo/addons/sale_cart/tests/__init__.py
odoo/addons/sale_cart/tests/common.py
odoo/addons/sale_cart/tests/test_sale_cart.py
odoo/addons/sale_cart/tests/test_sale_cart_payment.py
odoo/addons/sale_cart/views/sale_order.xml
odoo_addon_sale_cart-16.0.1.1.0.dist-info/METADATA
odoo_addon_sale_cart-16.0.1.1.0.dist-info/WHEEL
odoo_addon_sale_cart-16.0.1.1.0.dist-info/top_level.txt
odoo_addon_sale_cart-16.0.1.1.0.dist-info/RECORD
