Metadata-Version: 2.1
Name: odoo-addon-sale_cart
Version: 16.0.1.1.0
Summary: Uee Sale Orders as cart.
Home-page: https://github.com/shopinvader/odoo-shopinvader
Author: ACSONE SA/NV
License: AGPL-3
Classifier: Programming Language :: Python
Classifier: Framework :: Odoo
Classifier: Framework :: Odoo :: 16.0
Classifier: License :: OSI Approved :: GNU Affero General Public License v3
Requires-Python: >=3.10
Requires-Dist: odoo<16.1dev,>=16.0a
Requires-Dist: openupgradelib
